<bibdata>
  
  <title format="text/plain" language="en" script="Latn">101st meeting of the CIPM</title>
  <title format="text/plain" language="fr" script="Latn">101e réunion du CIPM</title>
  <uri type="src">https://raw.githubusercontent.com/relaton/relaton-data-w3c/main/data/PV-101.yaml</uri>
  <docidentifier type="BIPM" primary="true">BIPM PV 101</docidentifier>
  <date type="published">
    <on>2012-06-08</on>
  </date>
  <contributor>
    <role type="publisher"/>
    <organization>
      <name>Bureau International des Poids et Mesures</name>
      <abbreviation>BIPM</abbreviation>
      <uri>www.bipm.org</uri>
    </organization>
  </contributor>
  <language>en</language>
  <language>fr</language>
  <script>Latn</script>
  <relation type="partOf">
    <bibitem>
      <title format="text/plain" language="en" script="Latn">101st meeting of the CIPM (Session I)</title>
      <title format="text/plain" language="fr" script="Latn">101e réunion du CIPM (Partie I)</title>
      <uri type="src">https://www.bipm.org/en/committees/ci/cipm/101-_1-2012</uri>
      <docidentifier type="BIPM" primary="true">BIPM PV 101</docidentifier>
      <date type="published">
        <on>2012-06-08</on>
      </date>
      <contributor>
        <role type="publisher"/>
        <organization>
          <name>Bureau International des Poids et Mesures</name>
          <abbreviation>BIPM</abbreviation>
          <uri>www.bipm.org</uri>
        </organization>
      </contributor>
      <language>en</language>
      <language>fr</language>
      <script>Latn</script>
    </bibitem>
  </relation>
  <relation type="partOf">
    <bibitem>
      <title format="text/plain" language="en" script="Latn">101st meeting of the CIPM (Session II)</title>
      <title format="text/plain" language="fr" script="Latn">101e réunion du CIPM (Partie II)</title>
      <uri type="src">https://www.bipm.org/en/committees/ci/cipm/101-_2-2012</uri>
      <docidentifier type="BIPM" primary="true">BIPM PV 101</docidentifier>
      <date type="published">
        <on>2012-10-19</on>
      </date>
      <contributor>
        <role type="publisher"/>
        <organization>
          <name>Bureau International des Poids et Mesures</name>
          <abbreviation>BIPM</abbreviation>
          <uri>www.bipm.org</uri>
        </organization>
      </contributor>
      <language>en</language>
      <language>fr</language>
      <script>Latn</script>
    </bibitem>
  </relation>
  <ext>
    <doctype>meeting</doctype>
    <structuredidentifier>
      <docnumber>101</docnumber>
    </structuredidentifier>
  </ext>
</bibdata>